[
    {
        "SeasonId": 10,
        "OrderNumber": 1,
        "_tab": "<flatbuffers.table.Table object at 0x7fc1b876a830>"
    },
    {
        "SeasonId": 10,
        "OrderNumber": 2,
        "_tab": "<flatbuffers.table.Table object at 0x7fc1aceea350>"
    },
    {
        "SeasonId": 10,
        "OrderNumber": 3,
        "_tab": "<flatbuffers.table.Table object at 0x7fc1acee88b0>"
    },
    {
        "SeasonId": 10,
        "OrderNumber": 4,
        "_tab": "<flatbuffers.table.Table object at 0x7fc1acee80a0>"
    },
    {
        "SeasonId": 10,
        "OrderNumber": 5,
        "_tab": "<flatbuffers.table.Table object at 0x7fc1b7fce4d0>"
    },
    {
        "SeasonId": 10,
        "OrderNumber": 6,
        "_tab": "<flatbuffers.table.Table object at 0x7fc1b812e350>"
    },
    {
        "SeasonId": 10,
        "OrderNumber": 7,
        "_tab": "<flatbuffers.table.Table object at 0x7fc1ac5ed870>"
    },
    {
        "SeasonId": 10,
        "OrderNumber": 8,
        "_tab": "<flatbuffers.table.Table object at 0x7fc1ac5ec250>"
    },
    {
        "SeasonId": 10,
        "OrderNumber": 9,
        "_tab": "<flatbuffers.table.Table object at 0x7fc1ac5edcf0>"
    }
]