[
    {
        "Id": 10000,
        "_tab": "<flatbuffers.table.Table object at 0x7f113a7658a0>"
    },
    {
        "Id": 10001,
        "_tab": "<flatbuffers.table.Table object at 0x7f113a767610>"
    },
    {
        "Id": 10002,
        "_tab": "<flatbuffers.table.Table object at 0x7f113a7670d0>"
    },
    {
        "Id": 10003,
        "_tab": "<flatbuffers.table.Table object at 0x7f113a736650>"
    },
    {
        "Id": 10004,
        "_tab": "<flatbuffers.table.Table object at 0x7f113aa833d0>"
    },
    {
        "Id": 10005,
        "_tab": "<flatbuffers.table.Table object at 0x7f113aa82d10>"
    },
    {
        "Id": 1000501,
        "_tab": "<flatbuffers.table.Table object at 0x7f113aa83040>"
    },
    {
        "Id": 10006,
        "_tab": "<flatbuffers.table.Table object at 0x7f113aa827d0>"
    },
    {
        "Id": 10007,
        "_tab": "<flatbuffers.table.Table object at 0x7f113aa80400>"
    },
    {
        "Id": 10008,
        "_tab": "<flatbuffers.table.Table object at 0x7f113aa83100>"
    },
    {
        "Id": 10009,
        "_tab": "<flatbuffers.table.Table object at 0x7f113a740dc0>"
    },
    {
        "Id": 10010,
        "_tab": "<flatbuffers.table.Table object at 0x7f113a741570>"
    },
    {
        "Id": 1001001,
        "_tab": "<flatbuffers.table.Table object at 0x7f113a7420e0>"
    },
    {
        "Id": 10011,
        "_tab": "<flatbuffers.table.Table object at 0x7f113a742890>"
    },
    {
        "Id": 10012,
        "_tab": "<flatbuffers.table.Table object at 0x7f113aa27010>"
    },
    {
        "Id": 10013,
        "_tab": "<flatbuffers.table.Table object at 0x7f113a4f7010>"
    },
    {
        "Id": 10014,
        "_tab": "<flatbuffers.table.Table object at 0x7f113a4f6620>"
    },
    {
        "Id": 10015,
        "_tab": "<flatbuffers.table.Table object at 0x7f113a4f6da0>"
    },
    {
        "Id": 10016,
        "_tab": "<flatbuffers.table.Table object at 0x7f113aa80940>"
    },
    {
        "Id": 13000,
        "_tab": "<flatbuffers.table.Table object at 0x7f113aa81d80>"
    },
    {
        "Id": 13001,
        "_tab": "<flatbuffers.table.Table object at 0x7f113aa83430>"
    },
    {
        "Id": 13002,
        "_tab": "<flatbuffers.table.Table object at 0x7f113aa83ca0>"
    },
    {
        "Id": 13003,
        "_tab": "<flatbuffers.table.Table object at 0x7f113aa83280>"
    },
    {
        "Id": 13004,
        "_tab": "<flatbuffers.table.Table object at 0x7f113a735b70>"
    },
    {
        "Id": 1300401,
        "_tab": "<flatbuffers.table.Table object at 0x7f113a734c70>"
    },
    {
        "Id": 13005,
        "_tab": "<flatbuffers.table.Table object at 0x7f113a742830>"
    },
    {
        "Id": 13006,
        "_tab": "<flatbuffers.table.Table object at 0x7f113a4f7070>"
    },
    {
        "Id": 13007,
        "_tab": "<flatbuffers.table.Table object at 0x7f113a7411b0>"
    },
    {
        "Id": 13008,
        "_tab": "<flatbuffers.table.Table object at 0x7f113a743dc0>"
    },
    {
        "Id": 1300801,
        "_tab": "<flatbuffers.table.Table object at 0x7f113a7417b0>"
    },
    {
        "Id": 13009,
        "_tab": "<flatbuffers.table.Table object at 0x7f113a7668f0>"
    },
    {
        "Id": 13010,
        "_tab": "<flatbuffers.table.Table object at 0x7f113a7655d0>"
    },
    {
        "Id": 13011,
        "_tab": "<flatbuffers.table.Table object at 0x7f113a767a60>"
    },
    {
        "Id": 20000,
        "_tab": "<flatbuffers.table.Table object at 0x7f113a767370>"
    },
    {
        "Id": 20001,
        "_tab": "<flatbuffers.table.Table object at 0x7f113a4195d0>"
    },
    {
        "Id": 20002,
        "_tab": "<flatbuffers.table.Table object at 0x7f113a41b850>"
    },
    {
        "Id": 20003,
        "_tab": "<flatbuffers.table.Table object at 0x7f113a419f30>"
    },
    {
        "Id": 23000,
        "_tab": "<flatbuffers.table.Table object at 0x7f113a41ac50>"
    },
    {
        "Id": 23001,
        "_tab": "<flatbuffers.table.Table object at 0x7f113a41a890>"
    },
    {
        "Id": 23002,
        "_tab": "<flatbuffers.table.Table object at 0x7f113a4192d0>"
    },
    {
        "Id": 23003,
        "_tab": "<flatbuffers.table.Table object at 0x7f113aa25b10>"
    },
    {
        "Id": 23004,
        "_tab": "<flatbuffers.table.Table object at 0x7f113aa25bd0>"
    },
    {
        "Id": 23005,
        "_tab": "<flatbuffers.table.Table object at 0x7f113a7165f0>"
    },
    {
        "Id": 2300501,
        "_tab": "<flatbuffers.table.Table object at 0x7f113a714ac0>"
    },
    {
        "Id": 23006,
        "_tab": "<flatbuffers.table.Table object at 0x7f113aa272b0>"
    },
    {
        "Id": 10017,
        "_tab": "<flatbuffers.table.Table object at 0x7f113aa27a60>"
    },
    {
        "Id": 26006,
        "_tab": "<flatbuffers.table.Table object at 0x7f113aa27190>"
    },
    {
        "Id": 10018,
        "_tab": "<flatbuffers.table.Table object at 0x7f113a4192a0>"
    },
    {
        "Id": 10019,
        "_tab": "<flatbuffers.table.Table object at 0x7f113a419d20>"
    },
    {
        "Id": 10020,
        "_tab": "<flatbuffers.table.Table object at 0x7f113a41bf40>"
    },
    {
        "Id": 23007,
        "_tab": "<flatbuffers.table.Table object at 0x7f113a419390>"
    },
    {
        "Id": 26005,
        "_tab": "<flatbuffers.table.Table object at 0x7f113a41aa70>"
    },
    {
        "Id": 10021,
        "_tab": "<flatbuffers.table.Table object at 0x7f113a765ab0>"
    },
    {
        "Id": 16005,
        "_tab": "<flatbuffers.table.Table object at 0x7f113a7657b0>"
    },
    {
        "Id": 20004,
        "_tab": "<flatbuffers.table.Table object at 0x7f113a766290>"
    },
    {
        "Id": 20005,
        "_tab": "<flatbuffers.table.Table object at 0x7f113a766530>"
    },
    {
        "Id": 16006,
        "_tab": "<flatbuffers.table.Table object at 0x7f113a764d30>"
    },
    {
        "Id": 10022,
        "_tab": "<flatbuffers.table.Table object at 0x7f113a743970>"
    },
    {
        "Id": 10023,
        "_tab": "<flatbuffers.table.Table object at 0x7f113a7424d0>"
    },
    {
        "Id": 10024,
        "_tab": "<flatbuffers.table.Table object at 0x7f113a743d60>"
    },
    {
        "Id": 10025,
        "_tab": "<flatbuffers.table.Table object at 0x7f113a742860>"
    },
    {
        "Id": 13012,
        "_tab": "<flatbuffers.table.Table object at 0x7f113a741000>"
    },
    {
        "Id": 20006,
        "_tab": "<flatbuffers.table.Table object at 0x7f113a736650>"
    },
    {
        "Id": 10026,
        "_tab": "<flatbuffers.table.Table object at 0x7f113aa822f0>"
    },
    {
        "Id": 10027,
        "_tab": "<flatbuffers.table.Table object at 0x7f113aa811b0>"
    },
    {
        "Id": 10028,
        "_tab": "<flatbuffers.table.Table object at 0x7f113aa80f10>"
    },
    {
        "Id": 26003,
        "_tab": "<flatbuffers.table.Table object at 0x7f113aa83c10>"
    },
    {
        "Id": 10029,
        "_tab": "<flatbuffers.table.Table object at 0x7f113aa81d50>"
    },
    {
        "Id": 23008,
        "_tab": "<flatbuffers.table.Table object at 0x7f113a4f7070>"
    },
    {
        "Id": 20007,
        "_tab": "<flatbuffers.table.Table object at 0x7f113a715240>"
    },
    {
        "Id": 20008,
        "_tab": "<flatbuffers.table.Table object at 0x7f113aa582e0>"
    },
    {
        "Id": 20009,
        "_tab": "<flatbuffers.table.Table object at 0x7f113aa59390>"
    },
    {
        "Id": 10030,
        "_tab": "<flatbuffers.table.Table object at 0x7f113a7146a0>"
    },
    {
        "Id": 16007,
        "_tab": "<flatbuffers.table.Table object at 0x7f113a4f7e80>"
    },
    {
        "Id": 20010,
        "_tab": "<flatbuffers.table.Table object at 0x7f113aa80550>"
    },
    {
        "Id": 16000,
        "_tab": "<flatbuffers.table.Table object at 0x7f113aa81420>"
    },
    {
        "Id": 10031,
        "_tab": "<flatbuffers.table.Table object at 0x7f113aa82d10>"
    },
    {
        "Id": 10032,
        "_tab": "<flatbuffers.table.Table object at 0x7f113aa80910>"
    },
    {
        "Id": 20011,
        "_tab": "<flatbuffers.table.Table object at 0x7f113aa80250>"
    },
    {
        "Id": 16002,
        "_tab": "<flatbuffers.table.Table object at 0x7f113a737340>"
    },
    {
        "Id": 10033,
        "_tab": "<flatbuffers.table.Table object at 0x7f113a743fa0>"
    },
    {
        "Id": 20012,
        "_tab": "<flatbuffers.table.Table object at 0x7f113a742500>"
    },
    {
        "Id": 20013,
        "_tab": "<flatbuffers.table.Table object at 0x7f113a740100>"
    },
    {
        "Id": 16008,
        "_tab": "<flatbuffers.table.Table object at 0x7f113a741300>"
    },
    {
        "Id": 10034,
        "_tab": "<flatbuffers.table.Table object at 0x7f113a743e80>"
    },
    {
        "Id": 10035,
        "_tab": "<flatbuffers.table.Table object at 0x7f113a766260>"
    },
    {
        "Id": 10036,
        "_tab": "<flatbuffers.table.Table object at 0x7f113a764310>"
    },
    {
        "Id": 10037,
        "_tab": "<flatbuffers.table.Table object at 0x7f113a7668c0>"
    },
    {
        "Id": 10038,
        "_tab": "<flatbuffers.table.Table object at 0x7f113a7652a0>"
    },
    {
        "Id": 20014,
        "_tab": "<flatbuffers.table.Table object at 0x7f113a766980>"
    },
    {
        "Id": 10039,
        "_tab": "<flatbuffers.table.Table object at 0x7f113a41ab30>"
    },
    {
        "Id": 20015,
        "_tab": "<flatbuffers.table.Table object at 0x7f113a419c90>"
    },
    {
        "Id": 20016,
        "_tab": "<flatbuffers.table.Table object at 0x7f113a419f60>"
    },
    {
        "Id": 16009,
        "_tab": "<flatbuffers.table.Table object at 0x7f113a419e40>"
    },
    {
        "Id": 10040,
        "_tab": "<flatbuffers.table.Table object at 0x7f113a41a5f0>"
    },
    {
        "Id": 26004,
        "_tab": "<flatbuffers.table.Table object at 0x7f113aa27a00>"
    },
    {
        "Id": 10041,
        "_tab": "<flatbuffers.table.Table object at 0x7f113aa270d0>"
    },
    {
        "Id": 20017,
        "_tab": "<flatbuffers.table.Table object at 0x7f113aa25f60>"
    },
    {
        "Id": 10042,
        "_tab": "<flatbuffers.table.Table object at 0x7f113aa59330>"
    },
    {
        "Id": 16003,
        "_tab": "<flatbuffers.table.Table object at 0x7f113aa27fa0>"
    },
    {
        "Id": 10043,
        "_tab": "<flatbuffers.table.Table object at 0x7f113aa27730>"
    },
    {
        "Id": 10044,
        "_tab": "<flatbuffers.table.Table object at 0x7f113aa26410>"
    },
    {
        "Id": 26007,
        "_tab": "<flatbuffers.table.Table object at 0x7f113a418520>"
    },
    {
        "Id": 16004,
        "_tab": "<flatbuffers.table.Table object at 0x7f113a41b9a0>"
    },
    {
        "Id": 10045,
        "_tab": "<flatbuffers.table.Table object at 0x7f113a418f10>"
    },
    {
        "Id": 26008,
        "_tab": "<flatbuffers.table.Table object at 0x7f113a41b430>"
    },
    {
        "Id": 10046,
        "_tab": "<flatbuffers.table.Table object at 0x7f113a764ca0>"
    },
    {
        "Id": 10047,
        "_tab": "<flatbuffers.table.Table object at 0x7f113a765870>"
    },
    {
        "Id": 10048,
        "_tab": "<flatbuffers.table.Table object at 0x7f113a7653c0>"
    },
    {
        "Id": 26000,
        "_tab": "<flatbuffers.table.Table object at 0x7f113a767cd0>"
    },
    {
        "Id": 20018,
        "_tab": "<flatbuffers.table.Table object at 0x7f113a764df0>"
    },
    {
        "Id": 10049,
        "_tab": "<flatbuffers.table.Table object at 0x7f113a743a30>"
    },
    {
        "Id": 10050,
        "_tab": "<flatbuffers.table.Table object at 0x7f113a7421a0>"
    },
    {
        "Id": 10051,
        "_tab": "<flatbuffers.table.Table object at 0x7f113a743be0>"
    },
    {
        "Id": 10052,
        "_tab": "<flatbuffers.table.Table object at 0x7f113a7400a0>"
    },
    {
        "Id": 16010,
        "_tab": "<flatbuffers.table.Table object at 0x7f113a741e40>"
    },
    {
        "Id": 16001,
        "_tab": "<flatbuffers.table.Table object at 0x7f113a735330>"
    },
    {
        "Id": 20019,
        "_tab": "<flatbuffers.table.Table object at 0x7f113aa83430>"
    },
    {
        "Id": 10053,
        "_tab": "<flatbuffers.table.Table object at 0x7f113aa804c0>"
    },
    {
        "Id": 10054,
        "_tab": "<flatbuffers.table.Table object at 0x7f113aa82410>"
    },
    {
        "Id": 16011,
        "_tab": "<flatbuffers.table.Table object at 0x7f113aa81de0>"
    },
    {
        "Id": 20020,
        "_tab": "<flatbuffers.table.Table object at 0x7f113aa81720>"
    },
    {
        "Id": 26001,
        "_tab": "<flatbuffers.table.Table object at 0x7f113aa80c10>"
    },
    {
        "Id": 10055,
        "_tab": "<flatbuffers.table.Table object at 0x7f113a4f7df0>"
    },
    {
        "Id": 10056,
        "_tab": "<flatbuffers.table.Table object at 0x7f113aa27fa0>"
    },
    {
        "Id": 20021,
        "_tab": "<flatbuffers.table.Table object at 0x7f113a4cb1f0>"
    },
    {
        "Id": 26002,
        "_tab": "<flatbuffers.table.Table object at 0x7f113a716890>"
    },
    {
        "Id": 10057,
        "_tab": "<flatbuffers.table.Table object at 0x7f113aa81cf0>"
    },
    {
        "Id": 16012,
        "_tab": "<flatbuffers.table.Table object at 0x7f113aa81360>"
    },
    {
        "Id": 20022,
        "_tab": "<flatbuffers.table.Table object at 0x7f113aa80100>"
    },
    {
        "Id": 10058,
        "_tab": "<flatbuffers.table.Table object at 0x7f113aa80340>"
    },
    {
        "Id": 10059,
        "_tab": "<flatbuffers.table.Table object at 0x7f113aa80d60>"
    },
    {
        "Id": 20023,
        "_tab": "<flatbuffers.table.Table object at 0x7f113aa81d20>"
    },
    {
        "Id": 10060,
        "_tab": "<flatbuffers.table.Table object at 0x7f113a7358a0>"
    },
    {
        "Id": 10061,
        "_tab": "<flatbuffers.table.Table object at 0x7f113a741990>"
    },
    {
        "Id": 10062,
        "_tab": "<flatbuffers.table.Table object at 0x7f113a7412d0>"
    },
    {
        "Id": 20024,
        "_tab": "<flatbuffers.table.Table object at 0x7f113a740220>"
    },
    {
        "Id": 10063,
        "_tab": "<flatbuffers.table.Table object at 0x7f113a743c10>"
    },
    {
        "Id": 10064,
        "_tab": "<flatbuffers.table.Table object at 0x7f113b907f70>"
    },
    {
        "Id": 20025,
        "_tab": "<flatbuffers.table.Table object at 0x7f113a7642b0>"
    },
    {
        "Id": 10065,
        "_tab": "<flatbuffers.table.Table object at 0x7f113a764280>"
    },
    {
        "Id": 10066,
        "_tab": "<flatbuffers.table.Table object at 0x7f113a7664d0>"
    },
    {
        "Id": 10067,
        "_tab": "<flatbuffers.table.Table object at 0x7f113a765f60>"
    },
    {
        "Id": 26009,
        "_tab": "<flatbuffers.table.Table object at 0x7f113b626710>"
    },
    {
        "Id": 10068,
        "_tab": "<flatbuffers.table.Table object at 0x7f113a41a950>"
    },
    {
        "Id": 10069,
        "_tab": "<flatbuffers.table.Table object at 0x7f113a41bac0>"
    },
    {
        "Id": 10070,
        "_tab": "<flatbuffers.table.Table object at 0x7f113a4187f0>"
    },
    {
        "Id": 20026,
        "_tab": "<flatbuffers.table.Table object at 0x7f113a41aef0>"
    },
    {
        "Id": 10071,
        "_tab": "<flatbuffers.table.Table object at 0x7f113a41a5c0>"
    },
    {
        "Id": 10072,
        "_tab": "<flatbuffers.table.Table object at 0x7f113aa26650>"
    },
    {
        "Id": 26010,
        "_tab": "<flatbuffers.table.Table object at 0x7f113aa27e80>"
    },
    {
        "Id": 20027,
        "_tab": "<flatbuffers.table.Table object at 0x7f113a4cb9a0>"
    },
    {
        "Id": 10073,
        "_tab": "<flatbuffers.table.Table object at 0x7f113aa8c190>"
    },
    {
        "Id": 20028,
        "_tab": "<flatbuffers.table.Table object at 0x7f113a4cb790>"
    },
    {
        "Id": 16013,
        "_tab": "<flatbuffers.table.Table object at 0x7f113aa27d90>"
    },
    {
        "Id": 10074,
        "_tab": "<flatbuffers.table.Table object at 0x7f113aa26410>"
    },
    {
        "Id": 20029,
        "_tab": "<flatbuffers.table.Table object at 0x7f113a41a2c0>"
    },
    {
        "Id": 10075,
        "_tab": "<flatbuffers.table.Table object at 0x7f113a41a4a0>"
    },
    {
        "Id": 13013,
        "_tab": "<flatbuffers.table.Table object at 0x7f113a41b0a0>"
    },
    {
        "Id": 10076,
        "_tab": "<flatbuffers.table.Table object at 0x7f113a419e10>"
    },
    {
        "Id": 20030,
        "_tab": "<flatbuffers.table.Table object at 0x7f113a419360>"
    },
    {
        "Id": 10077,
        "_tab": "<flatbuffers.table.Table object at 0x7f113a767b80>"
    },
    {
        "Id": 10078,
        "_tab": "<flatbuffers.table.Table object at 0x7f113a764790>"
    },
    {
        "Id": 20031,
        "_tab": "<flatbuffers.table.Table object at 0x7f113a765030>"
    },
    {
        "Id": 10079,
        "_tab": "<flatbuffers.table.Table object at 0x7f113a767130>"
    },
    {
        "Id": 10080,
        "_tab": "<flatbuffers.table.Table object at 0x7f113a766590>"
    },
    {
        "Id": 26011,
        "_tab": "<flatbuffers.table.Table object at 0x7f113a767cd0>"
    },
    {
        "Id": 10081,
        "_tab": "<flatbuffers.table.Table object at 0x7f113a741f60>"
    },
    {
        "Id": 10082,
        "_tab": "<flatbuffers.table.Table object at 0x7f113a741150>"
    },
    {
        "Id": 10083,
        "_tab": "<flatbuffers.table.Table object at 0x7f113a7435b0>"
    },
    {
        "Id": 20032,
        "_tab": "<flatbuffers.table.Table object at 0x7f113a741720>"
    },
    {
        "Id": 10084,
        "_tab": "<flatbuffers.table.Table object at 0x7f113a734e50>"
    },
    {
        "Id": 10085,
        "_tab": "<flatbuffers.table.Table object at 0x7f113aa836a0>"
    },
    {
        "Id": 20033,
        "_tab": "<flatbuffers.table.Table object at 0x7f113aa817b0>"
    },
    {
        "Id": 10087,
        "_tab": "<flatbuffers.table.Table object at 0x7f113aa80a90>"
    },
    {
        "Id": 16014,
        "_tab": "<flatbuffers.table.Table object at 0x7f113aa81540>"
    },
    {
        "Id": 10086,
        "_tab": "<flatbuffers.table.Table object at 0x7f113aa820e0>"
    },
    {
        "Id": 10088,
        "_tab": "<flatbuffers.table.Table object at 0x7f113a4f5030>"
    },
    {
        "Id": 10089,
        "_tab": "<flatbuffers.table.Table object at 0x7f113aa8c7f0>"
    },
    {
        "Id": 20034,
        "_tab": "<flatbuffers.table.Table object at 0x7f113aa8cf70>"
    },
    {
        "Id": 10090,
        "_tab": "<flatbuffers.table.Table object at 0x7f113a4f41c0>"
    },
    {
        "Id": 20035,
        "_tab": "<flatbuffers.table.Table object at 0x7f113aa82170>"
    },
    {
        "Id": 10091,
        "_tab": "<flatbuffers.table.Table object at 0x7f113aa83bb0>"
    },
    {
        "Id": 16015,
        "_tab": "<flatbuffers.table.Table object at 0x7f113aa80070>"
    },
    {
        "Id": 10092,
        "_tab": "<flatbuffers.table.Table object at 0x7f113aa82c20>"
    },
    {
        "Id": 10093,
        "_tab": "<flatbuffers.table.Table object at 0x7f113aa83580>"
    },
    {
        "Id": 10094,
        "_tab": "<flatbuffers.table.Table object at 0x7f113a736650>"
    },
    {
        "Id": 10095,
        "_tab": "<flatbuffers.table.Table object at 0x7f113a735fc0>"
    },
    {
        "Id": 20036,
        "_tab": "<flatbuffers.table.Table object at 0x7f113a7426e0>"
    },
    {
        "Id": 10096,
        "_tab": "<flatbuffers.table.Table object at 0x7f113a7405e0>"
    },
    {
        "Id": 20037,
        "_tab": "<flatbuffers.table.Table object at 0x7f113a7409a0>"
    },
    {
        "Id": 26012,
        "_tab": "<flatbuffers.table.Table object at 0x7f113a743f70>"
    },
    {
        "Id": 10097,
        "_tab": "<flatbuffers.table.Table object at 0x7f113a767430>"
    },
    {
        "Id": 10098,
        "_tab": "<flatbuffers.table.Table object at 0x7f113a767100>"
    },
    {
        "Id": 10100,
        "_tab": "<flatbuffers.table.Table object at 0x7f113a766f80>"
    },
    {
        "Id": 10101,
        "_tab": "<flatbuffers.table.Table object at 0x7f113a764490>"
    },
    {
        "Id": 10102,
        "_tab": "<flatbuffers.table.Table object at 0x7f113a766740>"
    },
    {
        "Id": 26013,
        "_tab": "<flatbuffers.table.Table object at 0x7f113a419db0>"
    },
    {
        "Id": 10103,
        "_tab": "<flatbuffers.table.Table object at 0x7f113a767a90>"
    },
    {
        "Id": 20038,
        "_tab": "<flatbuffers.table.Table object at 0x7f113a418340>"
    },
    {
        "Id": 10104,
        "_tab": "<flatbuffers.table.Table object at 0x7f113a419960>"
    },
    {
        "Id": 20039,
        "_tab": "<flatbuffers.table.Table object at 0x7f113a4189d0>"
    },
    {
        "Id": 10105,
        "_tab": "<flatbuffers.table.Table object at 0x7f113aa25090>"
    },
    {
        "Id": 10106,
        "_tab": "<flatbuffers.table.Table object at 0x7f113aa268f0>"
    },
    {
        "Id": 16016,
        "_tab": "<flatbuffers.table.Table object at 0x7f113a4cb7c0>"
    },
    {
        "Id": 20040,
        "_tab": "<flatbuffers.table.Table object at 0x7f113aa8d720>"
    },
    {
        "Id": 10107,
        "_tab": "<flatbuffers.table.Table object at 0x7f113aa8ded0>"
    },
    {
        "Id": 10108,
        "_tab": "<flatbuffers.table.Table object at 0x7f113a4c9ff0>"
    },
    {
        "Id": 10109,
        "_tab": "<flatbuffers.table.Table object at 0x7f113aa26d10>"
    },
    {
        "Id": 10110,
        "_tab": "<flatbuffers.table.Table object at 0x7f113aa27370>"
    },
    {
        "Id": 10112,
        "_tab": "<flatbuffers.table.Table object at 0x7f113a418820>"
    },
    {
        "Id": 26014,
        "_tab": "<flatbuffers.table.Table object at 0x7f113a418ca0>"
    },
    {
        "Id": 20041,
        "_tab": "<flatbuffers.table.Table object at 0x7f113aa27a60>"
    },
    {
        "Id": 10111,
        "_tab": "<flatbuffers.table.Table object at 0x7f113a419c00>"
    },
    {
        "Id": 20042,
        "_tab": "<flatbuffers.table.Table object at 0x7f113a419e10>"
    },
    {
        "Id": 10113,
        "_tab": "<flatbuffers.table.Table object at 0x7f113a7671c0>"
    },
    {
        "Id": 10114,
        "_tab": "<flatbuffers.table.Table object at 0x7f113a767220>"
    },
    {
        "Id": 20043,
        "_tab": "<flatbuffers.table.Table object at 0x7f113a764370>"
    },
    {
        "Id": 20044,
        "_tab": "<flatbuffers.table.Table object at 0x7f113a766950>"
    },
    {
        "Id": 10115,
        "_tab": "<flatbuffers.table.Table object at 0x7f113a767cd0>"
    },
    {
        "Id": 10116,
        "_tab": "<flatbuffers.table.Table object at 0x7f113a741300>"
    },
    {
        "Id": 10117,
        "_tab": "<flatbuffers.table.Table object at 0x7f113a742260>"
    },
    {
        "Id": 10118,
        "_tab": "<flatbuffers.table.Table object at 0x7f113a740610>"
    },
    {
        "Id": 16017,
        "_tab": "<flatbuffers.table.Table object at 0x7f113a742920>"
    },
    {
        "Id": 20045,
        "_tab": "<flatbuffers.table.Table object at 0x7f113a7371c0>"
    },
    {
        "Id": 10119,
        "_tab": "<flatbuffers.table.Table object at 0x7f113a735180>"
    },
    {
        "Id": 20046,
        "_tab": "<flatbuffers.table.Table object at 0x7f113aa80c40>"
    },
    {
        "Id": 10120,
        "_tab": "<flatbuffers.table.Table object at 0x7f113aa80f40>"
    }
]