[
    {
        "Id": 1000,
        "_tab": "<flatbuffers.table.Table object at 0x7fc1b82177c0>"
    },
    {
        "Id": 1001,
        "_tab": "<flatbuffers.table.Table object at 0x7fc1b810bb20>"
    },
    {
        "Id": 1002,
        "_tab": "<flatbuffers.table.Table object at 0x7fc1aceeba60>"
    },
    {
        "Id": 1003,
        "_tab": "<flatbuffers.table.Table object at 0x7fc1acefc910>"
    },
    {
        "Id": 1004,
        "_tab": "<flatbuffers.table.Table object at 0x7fc1acc576d0>"
    },
    {
        "Id": 1005,
        "_tab": "<flatbuffers.table.Table object at 0x7fc1acc56950>"
    },
    {
        "Id": 1006,
        "_tab": "<flatbuffers.table.Table object at 0x7fc1acc56e30>"
    },
    {
        "Id": 1100,
        "_tab": "<flatbuffers.table.Table object at 0x7fc1acc57f10>"
    },
    {
        "Id": 1101,
        "_tab": "<flatbuffers.table.Table object at 0x7fc1b873ac80>"
    },
    {
        "Id": 1102,
        "_tab": "<flatbuffers.table.Table object at 0x7fc1b8739a20>"
    },
    {
        "Id": 1103,
        "_tab": "<flatbuffers.table.Table object at 0x7fc1b873bcd0>"
    },
    {
        "Id": 1104,
        "_tab": "<flatbuffers.table.Table object at 0x7fc1b8706c20>"
    },
    {
        "Id": 1105,
        "_tab": "<flatbuffers.table.Table object at 0x7fc1ac8a99c0>"
    },
    {
        "Id": 1106,
        "_tab": "<flatbuffers.table.Table object at 0x7fc1ac8aba90>"
    },
    {
        "Id": 1107,
        "_tab": "<flatbuffers.table.Table object at 0x7fc1ac8aacb0>"
    },
    {
        "Id": 1108,
        "_tab": "<flatbuffers.table.Table object at 0x7fc1ac8a9a20>"
    },
    {
        "Id": 1109,
        "_tab": "<flatbuffers.table.Table object at 0x7fc1b1a44a90>"
    },
    {
        "Id": 1110,
        "_tab": "<flatbuffers.table.Table object at 0x7fc1b82143d0>"
    },
    {
        "Id": 1111,
        "_tab": "<flatbuffers.table.Table object at 0x7fc1b1a46530>"
    },
    {
        "Id": 1112,
        "_tab": "<flatbuffers.table.Table object at 0x7fc1ac8a9a20>"
    },
    {
        "Id": 1113,
        "_tab": "<flatbuffers.table.Table object at 0x7fc1ac8a8b80>"
    },
    {
        "Id": 1114,
        "_tab": "<flatbuffers.table.Table object at 0x7fc1ac8a9ed0>"
    },
    {
        "Id": 1206,
        "_tab": "<flatbuffers.table.Table object at 0x7fc1ac8a8790>"
    },
    {
        "Id": 1500,
        "_tab": "<flatbuffers.table.Table object at 0x7fc1b8707430>"
    },
    {
        "Id": 1501,
        "_tab": "<flatbuffers.table.Table object at 0x7fc1b8707a60>"
    },
    {
        "Id": 1502,
        "_tab": "<flatbuffers.table.Table object at 0x7fc1acc57940>"
    },
    {
        "Id": 1503,
        "_tab": "<flatbuffers.table.Table object at 0x7fc1acc54d00>"
    },
    {
        "Id": 1504,
        "_tab": "<flatbuffers.table.Table object at 0x7fc1acc553c0>"
    },
    {
        "Id": 1505,
        "_tab": "<flatbuffers.table.Table object at 0x7fc1acefcee0>"
    },
    {
        "Id": 1506,
        "_tab": "<flatbuffers.table.Table object at 0x7fc1acee9b40>"
    },
    {
        "Id": 1507,
        "_tab": "<flatbuffers.table.Table object at 0x7fc1aceea170>"
    },
    {
        "Id": 1508,
        "_tab": "<flatbuffers.table.Table object at 0x7fc1ac268fa0>"
    },
    {
        "Id": 1509,
        "_tab": "<flatbuffers.table.Table object at 0x7fc1b873ab30>"
    },
    {
        "Id": 1510,
        "_tab": "<flatbuffers.table.Table object at 0x7fc1b873b9d0>"
    },
    {
        "Id": 1511,
        "_tab": "<flatbuffers.table.Table object at 0x7fc1b8739240>"
    },
    {
        "Id": 1512,
        "_tab": "<flatbuffers.table.Table object at 0x7fc1b8214e80>"
    },
    {
        "Id": 1513,
        "_tab": "<flatbuffers.table.Table object at 0x7fc1b8215b10>"
    },
    {
        "Id": 1514,
        "_tab": "<flatbuffers.table.Table object at 0x7fc1b8214ca0>"
    },
    {
        "Id": 1515,
        "_tab": "<flatbuffers.table.Table object at 0x7fc1b1a47d30>"
    },
    {
        "Id": 1516,
        "_tab": "<flatbuffers.table.Table object at 0x7fc1b1a46320>"
    },
    {
        "Id": 1517,
        "_tab": "<flatbuffers.table.Table object at 0x7fc1b1a47490>"
    },
    {
        "Id": 1518,
        "_tab": "<flatbuffers.table.Table object at 0x7fc1b1a45540>"
    },
    {
        "Id": 1519,
        "_tab": "<flatbuffers.table.Table object at 0x7fc1b8217730>"
    },
    {
        "Id": 1520,
        "_tab": "<flatbuffers.table.Table object at 0x7fc1b8217bb0>"
    },
    {
        "Id": 1521,
        "_tab": "<flatbuffers.table.Table object at 0x7fc1b82158a0>"
    },
    {
        "Id": 1522,
        "_tab": "<flatbuffers.table.Table object at 0x7fc1b873a0b0>"
    },
    {
        "Id": 1523,
        "_tab": "<flatbuffers.table.Table object at 0x7fc1b873a230>"
    },
    {
        "Id": 1524,
        "_tab": "<flatbuffers.table.Table object at 0x7fc1b8739c30>"
    },
    {
        "Id": 1525,
        "_tab": "<flatbuffers.table.Table object at 0x7fc1b87388e0>"
    },
    {
        "Id": 1526,
        "_tab": "<flatbuffers.table.Table object at 0x7fc1b8108f40>"
    },
    {
        "Id": 1527,
        "_tab": "<flatbuffers.table.Table object at 0x7fc1aceea0e0>"
    },
    {
        "Id": 1528,
        "_tab": "<flatbuffers.table.Table object at 0x7fc1acefcca0>"
    },
    {
        "Id": 1529,
        "_tab": "<flatbuffers.table.Table object at 0x7fc1acc56290>"
    },
    {
        "Id": 1530,
        "_tab": "<flatbuffers.table.Table object at 0x7fc1acc54160>"
    },
    {
        "Id": 1531,
        "_tab": "<flatbuffers.table.Table object at 0x7fc1acc55ba0>"
    },
    {
        "Id": 1532,
        "_tab": "<flatbuffers.table.Table object at 0x7fc1acc54d60>"
    },
    {
        "Id": 1533,
        "_tab": "<flatbuffers.table.Table object at 0x7fc1b8707dc0>"
    },
    {
        "Id": 1534,
        "_tab": "<flatbuffers.table.Table object at 0x7fc1b8707d30>"
    },
    {
        "Id": 1535,
        "_tab": "<flatbuffers.table.Table object at 0x7fc1ac8ab190>"
    },
    {
        "Id": 1536,
        "_tab": "<flatbuffers.table.Table object at 0x7fc1ac8abcd0>"
    },
    {
        "Id": 1537,
        "_tab": "<flatbuffers.table.Table object at 0x7fc1ac8aacb0>"
    },
    {
        "Id": 1538,
        "_tab": "<flatbuffers.table.Table object at 0x7fc1b1a47f70>"
    },
    {
        "Id": 1539,
        "_tab": "<flatbuffers.table.Table object at 0x7fc1b1a468f0>"
    },
    {
        "Id": 1540,
        "_tab": "<flatbuffers.table.Table object at 0x7fc1b842d660>"
    },
    {
        "Id": 1541,
        "_tab": "<flatbuffers.table.Table object at 0x7fc1acc54d60>"
    },
    {
        "Id": 1542,
        "_tab": "<flatbuffers.table.Table object at 0x7fc1acc57460>"
    },
    {
        "Id": 1543,
        "_tab": "<flatbuffers.table.Table object at 0x7fc1acc56ec0>"
    },
    {
        "Id": 1544,
        "_tab": "<flatbuffers.table.Table object at 0x7fc1acc56a10>"
    },
    {
        "Id": 1545,
        "_tab": "<flatbuffers.table.Table object at 0x7fc1b1a44040>"
    },
    {
        "Id": 1546,
        "_tab": "<flatbuffers.table.Table object at 0x7fc1b1a45db0>"
    },
    {
        "Id": 1547,
        "_tab": "<flatbuffers.table.Table object at 0x7fc1b1a45690>"
    },
    {
        "Id": 1548,
        "_tab": "<flatbuffers.table.Table object at 0x7fc1b1a46380>"
    },
    {
        "Id": 1549,
        "_tab": "<flatbuffers.table.Table object at 0x7fc1b1a472b0>"
    },
    {
        "Id": 1550,
        "_tab": "<flatbuffers.table.Table object at 0x7fc1b81561d0>"
    },
    {
        "Id": 1551,
        "_tab": "<flatbuffers.table.Table object at 0x7fc1b8154130>"
    },
    {
        "Id": 1552,
        "_tab": "<flatbuffers.table.Table object at 0x7fc1acc54220>"
    },
    {
        "Id": 1553,
        "_tab": "<flatbuffers.table.Table object at 0x7fc1acefc8b0>"
    },
    {
        "Id": 1554,
        "_tab": "<flatbuffers.table.Table object at 0x7fc1b810a410>"
    },
    {
        "Id": 1555,
        "_tab": "<flatbuffers.table.Table object at 0x7fc1b8109060>"
    },
    {
        "Id": 1556,
        "_tab": "<flatbuffers.table.Table object at 0x7fc1ad0a98a0>"
    },
    {
        "Id": 1557,
        "_tab": "<flatbuffers.table.Table object at 0x7fc1ac8ab640>"
    },
    {
        "Id": 1558,
        "_tab": "<flatbuffers.table.Table object at 0x7fc1ac8a93c0>"
    },
    {
        "Id": 1559,
        "_tab": "<flatbuffers.table.Table object at 0x7fc1ac8ab910>"
    },
    {
        "Id": 1560,
        "_tab": "<flatbuffers.table.Table object at 0x7fc1ac8aa980>"
    },
    {
        "Id": 1561,
        "_tab": "<flatbuffers.table.Table object at 0x7fc1ac268fd0>"
    },
    {
        "Id": 1562,
        "_tab": "<flatbuffers.table.Table object at 0x7fc1ac26be80>"
    },
    {
        "Id": 1563,
        "_tab": "<flatbuffers.table.Table object at 0x7fc1ac269cc0>"
    },
    {
        "Id": 1564,
        "_tab": "<flatbuffers.table.Table object at 0x7fc1ac8a94e0>"
    },
    {
        "Id": 1565,
        "_tab": "<flatbuffers.table.Table object at 0x7fc1ac8a8820>"
    },
    {
        "Id": 1566,
        "_tab": "<flatbuffers.table.Table object at 0x7fc1ac8a8df0>"
    },
    {
        "Id": 1567,
        "_tab": "<flatbuffers.table.Table object at 0x7fc1ac8aa4a0>"
    },
    {
        "Id": 1568,
        "_tab": "<flatbuffers.table.Table object at 0x7fc1ad0aa6e0>"
    },
    {
        "Id": 1569,
        "_tab": "<flatbuffers.table.Table object at 0x7fc1b8109060>"
    },
    {
        "Id": 1570,
        "_tab": "<flatbuffers.table.Table object at 0x7fc1b810b6d0>"
    },
    {
        "Id": 1571,
        "_tab": "<flatbuffers.table.Table object at 0x7fc1acefdf30>"
    },
    {
        "Id": 1572,
        "_tab": "<flatbuffers.table.Table object at 0x7fc1acefd7b0>"
    },
    {
        "Id": 1573,
        "_tab": "<flatbuffers.table.Table object at 0x7fc1b81545e0>"
    },
    {
        "Id": 1574,
        "_tab": "<flatbuffers.table.Table object at 0x7fc1b81560b0>"
    },
    {
        "Id": 1575,
        "_tab": "<flatbuffers.table.Table object at 0x7fc1b1a44a60>"
    },
    {
        "Id": 1576,
        "_tab": "<flatbuffers.table.Table object at 0x7fc1b1a45780>"
    },
    {
        "Id": 1577,
        "_tab": "<flatbuffers.table.Table object at 0x7fc1b1a45480>"
    },
    {
        "Id": 1578,
        "_tab": "<flatbuffers.table.Table object at 0x7fc1b1a47d60>"
    },
    {
        "Id": 1579,
        "_tab": "<flatbuffers.table.Table object at 0x7fc1b1a466e0>"
    },
    {
        "Id": 1580,
        "_tab": "<flatbuffers.table.Table object at 0x7fc1acc56f20>"
    },
    {
        "Id": 1581,
        "_tab": "<flatbuffers.table.Table object at 0x7fc1acc576d0>"
    },
    {
        "Id": 1582,
        "_tab": "<flatbuffers.table.Table object at 0x7fc1acc57070>"
    },
    {
        "Id": 1583,
        "_tab": "<flatbuffers.table.Table object at 0x7fc1acc56e30>"
    },
    {
        "Id": 1584,
        "_tab": "<flatbuffers.table.Table object at 0x7fc1ac268f70>"
    },
    {
        "Id": 1585,
        "_tab": "<flatbuffers.table.Table object at 0x7fc1b8462e60>"
    },
    {
        "Id": 1586,
        "_tab": "<flatbuffers.table.Table object at 0x7fc1b84600a0>"
    },
    {
        "Id": 1587,
        "_tab": "<flatbuffers.table.Table object at 0x7fc1ac26b4f0>"
    },
    {
        "Id": 1588,
        "_tab": "<flatbuffers.table.Table object at 0x7fc1ac26a770>"
    },
    {
        "Id": 1589,
        "_tab": "<flatbuffers.table.Table object at 0x7fc1acc56740>"
    },
    {
        "Id": 1590,
        "_tab": "<flatbuffers.table.Table object at 0x7fc1acc579d0>"
    },
    {
        "Id": 1591,
        "_tab": "<flatbuffers.table.Table object at 0x7fc1acc57eb0>"
    },
    {
        "Id": 1592,
        "_tab": "<flatbuffers.table.Table object at 0x7fc1b1a45180>"
    },
    {
        "Id": 1593,
        "_tab": "<flatbuffers.table.Table object at 0x7fc1b1a452a0>"
    },
    {
        "Id": 1594,
        "_tab": "<flatbuffers.table.Table object at 0x7fc1b1a45cf0>"
    },
    {
        "Id": 1595,
        "_tab": "<flatbuffers.table.Table object at 0x7fc1b1a470a0>"
    },
    {
        "Id": 1596,
        "_tab": "<flatbuffers.table.Table object at 0x7fc1b1a44880>"
    },
    {
        "Id": 1597,
        "_tab": "<flatbuffers.table.Table object at 0x7fc1b8156740>"
    },
    {
        "Id": 1598,
        "_tab": "<flatbuffers.table.Table object at 0x7fc1b81577c0>"
    },
    {
        "Id": 1599,
        "_tab": "<flatbuffers.table.Table object at 0x7fc1acefd4e0>"
    },
    {
        "Id": 1600,
        "_tab": "<flatbuffers.table.Table object at 0x7fc1acefcbb0>"
    },
    {
        "Id": 1601,
        "_tab": "<flatbuffers.table.Table object at 0x7fc1acefea40>"
    },
    {
        "Id": 1602,
        "_tab": "<flatbuffers.table.Table object at 0x7fc1b810a860>"
    },
    {
        "Id": 1603,
        "_tab": "<flatbuffers.table.Table object at 0x7fc1ad0a9150>"
    },
    {
        "Id": 1604,
        "_tab": "<flatbuffers.table.Table object at 0x7fc1ac8a9c90>"
    },
    {
        "Id": 1605,
        "_tab": "<flatbuffers.table.Table object at 0x7fc1ac8a8460>"
    },
    {
        "Id": 1606,
        "_tab": "<flatbuffers.table.Table object at 0x7fc1ac8aa320>"
    },
    {
        "Id": 1607,
        "_tab": "<flatbuffers.table.Table object at 0x7fc1ac8aa620>"
    },
    {
        "Id": 1608,
        "_tab": "<flatbuffers.table.Table object at 0x7fc1b8707760>"
    },
    {
        "Id": 1609,
        "_tab": "<flatbuffers.table.Table object at 0x7fc1ac8aa230>"
    },
    {
        "Id": 1610,
        "_tab": "<flatbuffers.table.Table object at 0x7fc1ac8a8d00>"
    },
    {
        "Id": 1611,
        "_tab": "<flatbuffers.table.Table object at 0x7fc1ac8ab100>"
    },
    {
        "Id": 1612,
        "_tab": "<flatbuffers.table.Table object at 0x7fc1ad0aa8f0>"
    },
    {
        "Id": 1613,
        "_tab": "<flatbuffers.table.Table object at 0x7fc1ad0aabf0>"
    },
    {
        "Id": 1614,
        "_tab": "<flatbuffers.table.Table object at 0x7fc1b810a9b0>"
    },
    {
        "Id": 1615,
        "_tab": "<flatbuffers.table.Table object at 0x7fc1acefdbd0>"
    },
    {
        "Id": 1616,
        "_tab": "<flatbuffers.table.Table object at 0x7fc1aceff220>"
    },
    {
        "Id": 1617,
        "_tab": "<flatbuffers.table.Table object at 0x7fc1b81577c0>"
    },
    {
        "Id": 1618,
        "_tab": "<flatbuffers.table.Table object at 0x7fc1b8155b10>"
    },
    {
        "Id": 1619,
        "_tab": "<flatbuffers.table.Table object at 0x7fc1b8156560>"
    },
    {
        "Id": 1620,
        "_tab": "<flatbuffers.table.Table object at 0x7fc1b1a44df0>"
    },
    {
        "Id": 1621,
        "_tab": "<flatbuffers.table.Table object at 0x7fc1b1a458a0>"
    },
    {
        "Id": 1622,
        "_tab": "<flatbuffers.table.Table object at 0x7fc1b1a44580>"
    },
    {
        "Id": 1623,
        "_tab": "<flatbuffers.table.Table object at 0x7fc1b1a450c0>"
    },
    {
        "Id": 1624,
        "_tab": "<flatbuffers.table.Table object at 0x7fc1acc54220>"
    },
    {
        "Id": 1625,
        "_tab": "<flatbuffers.table.Table object at 0x7fc1acc57cd0>"
    },
    {
        "Id": 1626,
        "_tab": "<flatbuffers.table.Table object at 0x7fc1acc559c0>"
    },
    {
        "Id": 1627,
        "_tab": "<flatbuffers.table.Table object at 0x7fc1acc56c80>"
    },
    {
        "Id": 1628,
        "_tab": "<flatbuffers.table.Table object at 0x7fc1ac269b10>"
    },
    {
        "Id": 5000,
        "_tab": "<flatbuffers.table.Table object at 0x7fc1b8706230>"
    },
    {
        "Id": 5001,
        "_tab": "<flatbuffers.table.Table object at 0x7fc1b87390f0>"
    },
    {
        "Id": 5002,
        "_tab": "<flatbuffers.table.Table object at 0x7fc1b8738340>"
    },
    {
        "Id": 5003,
        "_tab": "<flatbuffers.table.Table object at 0x7fc1b8706da0>"
    },
    {
        "Id": 5004,
        "_tab": "<flatbuffers.table.Table object at 0x7fc1ac26add0>"
    },
    {
        "Id": 5005,
        "_tab": "<flatbuffers.table.Table object at 0x7fc1acc56a70>"
    },
    {
        "Id": 5006,
        "_tab": "<flatbuffers.table.Table object at 0x7fc1acc541c0>"
    },
    {
        "Id": 5100,
        "_tab": "<flatbuffers.table.Table object at 0x7fc1acc56f20>"
    },
    {
        "Id": 5101,
        "_tab": "<flatbuffers.table.Table object at 0x7fc1acc54370>"
    },
    {
        "Id": 5102,
        "_tab": "<flatbuffers.table.Table object at 0x7fc1b1a45090>"
    },
    {
        "Id": 5103,
        "_tab": "<flatbuffers.table.Table object at 0x7fc1b1a47df0>"
    },
    {
        "Id": 5104,
        "_tab": "<flatbuffers.table.Table object at 0x7fc1b1a456c0>"
    },
    {
        "Id": 5105,
        "_tab": "<flatbuffers.table.Table object at 0x7fc1b1a46dd0>"
    },
    {
        "Id": 5106,
        "_tab": "<flatbuffers.table.Table object at 0x7fc1b1a47280>"
    },
    {
        "Id": 5107,
        "_tab": "<flatbuffers.table.Table object at 0x7fc1b8156110>"
    },
    {
        "Id": 5108,
        "_tab": "<flatbuffers.table.Table object at 0x7fc1b8154bb0>"
    },
    {
        "Id": 5109,
        "_tab": "<flatbuffers.table.Table object at 0x7fc1acefff40>"
    },
    {
        "Id": 5110,
        "_tab": "<flatbuffers.table.Table object at 0x7fc1acefca90>"
    },
    {
        "Id": 5111,
        "_tab": "<flatbuffers.table.Table object at 0x7fc1b810bd00>"
    },
    {
        "Id": 5112,
        "_tab": "<flatbuffers.table.Table object at 0x7fc1b810a230>"
    },
    {
        "Id": 5113,
        "_tab": "<flatbuffers.table.Table object at 0x7fc1ad0a9cf0>"
    },
    {
        "Id": 5114,
        "_tab": "<flatbuffers.table.Table object at 0x7fc1ac8aae90>"
    },
    {
        "Id": 5206,
        "_tab": "<flatbuffers.table.Table object at 0x7fc1ac8a9390>"
    },
    {
        "Id": 5500,
        "_tab": "<flatbuffers.table.Table object at 0x7fc1b8154700>"
    },
    {
        "Id": 5501,
        "_tab": "<flatbuffers.table.Table object at 0x7fc1b8739630>"
    },
    {
        "Id": 5502,
        "_tab": "<flatbuffers.table.Table object at 0x7fc1b873aa40>"
    },
    {
        "Id": 5503,
        "_tab": "<flatbuffers.table.Table object at 0x7fc1b8739480>"
    },
    {
        "Id": 5504,
        "_tab": "<flatbuffers.table.Table object at 0x7fc1ac8a97e0>"
    },
    {
        "Id": 5505,
        "_tab": "<flatbuffers.table.Table object at 0x7fc1ac8aa4a0>"
    },
    {
        "Id": 5506,
        "_tab": "<flatbuffers.table.Table object at 0x7fc1ac8a8850>"
    },
    {
        "Id": 5507,
        "_tab": "<flatbuffers.table.Table object at 0x7fc1ad0a95a0>"
    },
    {
        "Id": 5508,
        "_tab": "<flatbuffers.table.Table object at 0x7fc1b810a140>"
    },
    {
        "Id": 5509,
        "_tab": "<flatbuffers.table.Table object at 0x7fc1acefdd20>"
    },
    {
        "Id": 5510,
        "_tab": "<flatbuffers.table.Table object at 0x7fc1aceff9a0>"
    },
    {
        "Id": 5511,
        "_tab": "<flatbuffers.table.Table object at 0x7fc1acefda20>"
    },
    {
        "Id": 5512,
        "_tab": "<flatbuffers.table.Table object at 0x7fc1b8156a10>"
    },
    {
        "Id": 5513,
        "_tab": "<flatbuffers.table.Table object at 0x7fc1b8156680>"
    },
    {
        "Id": 5514,
        "_tab": "<flatbuffers.table.Table object at 0x7fc1b1a46980>"
    },
    {
        "Id": 5515,
        "_tab": "<flatbuffers.table.Table object at 0x7fc1b1a46920>"
    },
    {
        "Id": 5516,
        "_tab": "<flatbuffers.table.Table object at 0x7fc1b1a459c0>"
    },
    {
        "Id": 5517,
        "_tab": "<flatbuffers.table.Table object at 0x7fc1b1a457e0>"
    },
    {
        "Id": 5518,
        "_tab": "<flatbuffers.table.Table object at 0x7fc1acc56920>"
    },
    {
        "Id": 5519,
        "_tab": "<flatbuffers.table.Table object at 0x7fc1acc55e10>"
    },
    {
        "Id": 5520,
        "_tab": "<flatbuffers.table.Table object at 0x7fc1acc56f50>"
    },
    {
        "Id": 5521,
        "_tab": "<flatbuffers.table.Table object at 0x7fc1acc57610>"
    },
    {
        "Id": 5522,
        "_tab": "<flatbuffers.table.Table object at 0x7fc1ac268220>"
    },
    {
        "Id": 5523,
        "_tab": "<flatbuffers.table.Table object at 0x7fc1b8707ac0>"
    },
    {
        "Id": 5524,
        "_tab": "<flatbuffers.table.Table object at 0x7fc1b8216200>"
    },
    {
        "Id": 5525,
        "_tab": "<flatbuffers.table.Table object at 0x7fc1b8706740>"
    },
    {
        "Id": 5526,
        "_tab": "<flatbuffers.table.Table object at 0x7fc1ac268880>"
    },
    {
        "Id": 5527,
        "_tab": "<flatbuffers.table.Table object at 0x7fc1acc55c00>"
    },
    {
        "Id": 5528,
        "_tab": "<flatbuffers.table.Table object at 0x7fc1acc561a0>"
    },
    {
        "Id": 5529,
        "_tab": "<flatbuffers.table.Table object at 0x7fc1acc54040>"
    },
    {
        "Id": 5530,
        "_tab": "<flatbuffers.table.Table object at 0x7fc1b1a450c0>"
    },
    {
        "Id": 5531,
        "_tab": "<flatbuffers.table.Table object at 0x7fc1b1a46d40>"
    },
    {
        "Id": 5532,
        "_tab": "<flatbuffers.table.Table object at 0x7fc1b1a44040>"
    },
    {
        "Id": 5533,
        "_tab": "<flatbuffers.table.Table object at 0x7fc1b1a46560>"
    },
    {
        "Id": 5534,
        "_tab": "<flatbuffers.table.Table object at 0x7fc1b1a44310>"
    },
    {
        "Id": 5535,
        "_tab": "<flatbuffers.table.Table object at 0x7fc1b81573a0>"
    },
    {
        "Id": 5536,
        "_tab": "<flatbuffers.table.Table object at 0x7fc1b8155720>"
    },
    {
        "Id": 5537,
        "_tab": "<flatbuffers.table.Table object at 0x7fc1aceffc70>"
    },
    {
        "Id": 5538,
        "_tab": "<flatbuffers.table.Table object at 0x7fc1acefefe0>"
    },
    {
        "Id": 5539,
        "_tab": "<flatbuffers.table.Table object at 0x7fc1b81095d0>"
    },
    {
        "Id": 5540,
        "_tab": "<flatbuffers.table.Table object at 0x7fc1b810a7a0>"
    },
    {
        "Id": 5541,
        "_tab": "<flatbuffers.table.Table object at 0x7fc1ad0aba30>"
    },
    {
        "Id": 5542,
        "_tab": "<flatbuffers.table.Table object at 0x7fc1ac8ab6a0>"
    },
    {
        "Id": 5543,
        "_tab": "<flatbuffers.table.Table object at 0x7fc1ac8abe50>"
    },
    {
        "Id": 5544,
        "_tab": "<flatbuffers.table.Table object at 0x7fc1ac8a9c30>"
    },
    {
        "Id": 5545,
        "_tab": "<flatbuffers.table.Table object at 0x7fc1b8214a90>"
    },
    {
        "Id": 5546,
        "_tab": "<flatbuffers.table.Table object at 0x7fc1b8214be0>"
    },
    {
        "Id": 5547,
        "_tab": "<flatbuffers.table.Table object at 0x7fc1b8215210>"
    },
    {
        "Id": 5548,
        "_tab": "<flatbuffers.table.Table object at 0x7fc1b8216710>"
    },
    {
        "Id": 5549,
        "_tab": "<flatbuffers.table.Table object at 0x7fc1b8739030>"
    },
    {
        "Id": 5550,
        "_tab": "<flatbuffers.table.Table object at 0x7fc1ac8a9360>"
    },
    {
        "Id": 5551,
        "_tab": "<flatbuffers.table.Table object at 0x7fc1ac8a8310>"
    },
    {
        "Id": 5552,
        "_tab": "<flatbuffers.table.Table object at 0x7fc1ac8a94e0>"
    },
    {
        "Id": 5553,
        "_tab": "<flatbuffers.table.Table object at 0x7fc1ad0aa830>"
    },
    {
        "Id": 5554,
        "_tab": "<flatbuffers.table.Table object at 0x7fc1b8108e20>"
    },
    {
        "Id": 5555,
        "_tab": "<flatbuffers.table.Table object at 0x7fc1acefd5d0>"
    },
    {
        "Id": 5556,
        "_tab": "<flatbuffers.table.Table object at 0x7fc1acefdc90>"
    },
    {
        "Id": 5557,
        "_tab": "<flatbuffers.table.Table object at 0x7fc1acefcca0>"
    },
    {
        "Id": 5558,
        "_tab": "<flatbuffers.table.Table object at 0x7fc1b8157040>"
    },
    {
        "Id": 5559,
        "_tab": "<flatbuffers.table.Table object at 0x7fc1b8154d60>"
    },
    {
        "Id": 5560,
        "_tab": "<flatbuffers.table.Table object at 0x7fc1b1a440d0>"
    },
    {
        "Id": 5561,
        "_tab": "<flatbuffers.table.Table object at 0x7fc1b1a44d30>"
    },
    {
        "Id": 5562,
        "_tab": "<flatbuffers.table.Table object at 0x7fc1b1a46470>"
    },
    {
        "Id": 5563,
        "_tab": "<flatbuffers.table.Table object at 0x7fc1b1a46da0>"
    },
    {
        "Id": 5564,
        "_tab": "<flatbuffers.table.Table object at 0x7fc1acc54370>"
    },
    {
        "Id": 5565,
        "_tab": "<flatbuffers.table.Table object at 0x7fc1acc56290>"
    },
    {
        "Id": 5566,
        "_tab": "<flatbuffers.table.Table object at 0x7fc1acc57160>"
    },
    {
        "Id": 5567,
        "_tab": "<flatbuffers.table.Table object at 0x7fc1acc57370>"
    },
    {
        "Id": 5568,
        "_tab": "<flatbuffers.table.Table object at 0x7fc1ac268f40>"
    },
    {
        "Id": 5569,
        "_tab": "<flatbuffers.table.Table object at 0x7fc1aceea200>"
    },
    {
        "Id": 5570,
        "_tab": "<flatbuffers.table.Table object at 0x7fc1aceea650>"
    },
    {
        "Id": 5571,
        "_tab": "<flatbuffers.table.Table object at 0x7fc1ac268190>"
    },
    {
        "Id": 5572,
        "_tab": "<flatbuffers.table.Table object at 0x7fc1acc56380>"
    },
    {
        "Id": 5573,
        "_tab": "<flatbuffers.table.Table object at 0x7fc1acc54130>"
    },
    {
        "Id": 5574,
        "_tab": "<flatbuffers.table.Table object at 0x7fc1acc570d0>"
    },
    {
        "Id": 5575,
        "_tab": "<flatbuffers.table.Table object at 0x7fc1acc57eb0>"
    },
    {
        "Id": 5576,
        "_tab": "<flatbuffers.table.Table object at 0x7fc1b1a446d0>"
    },
    {
        "Id": 5577,
        "_tab": "<flatbuffers.table.Table object at 0x7fc1b1a47460>"
    },
    {
        "Id": 5578,
        "_tab": "<flatbuffers.table.Table object at 0x7fc1b1a47610>"
    },
    {
        "Id": 5579,
        "_tab": "<flatbuffers.table.Table object at 0x7fc1b1a46ad0>"
    },
    {
        "Id": 5580,
        "_tab": "<flatbuffers.table.Table object at 0x7fc1b1a47820>"
    },
    {
        "Id": 5581,
        "_tab": "<flatbuffers.table.Table object at 0x7fc1b8155f30>"
    },
    {
        "Id": 5582,
        "_tab": "<flatbuffers.table.Table object at 0x7fc1b8154130>"
    },
    {
        "Id": 5583,
        "_tab": "<flatbuffers.table.Table object at 0x7fc1acefdb40>"
    },
    {
        "Id": 5584,
        "_tab": "<flatbuffers.table.Table object at 0x7fc1acefea40>"
    },
    {
        "Id": 5585,
        "_tab": "<flatbuffers.table.Table object at 0x7fc1b8109cc0>"
    },
    {
        "Id": 5586,
        "_tab": "<flatbuffers.table.Table object at 0x7fc1b8109b10>"
    },
    {
        "Id": 5587,
        "_tab": "<flatbuffers.table.Table object at 0x7fc1ad0a8550>"
    },
    {
        "Id": 5588,
        "_tab": "<flatbuffers.table.Table object at 0x7fc1ac8a86d0>"
    },
    {
        "Id": 5589,
        "_tab": "<flatbuffers.table.Table object at 0x7fc1ac8a8430>"
    },
    {
        "Id": 5590,
        "_tab": "<flatbuffers.table.Table object at 0x7fc1ac8a9d20>"
    },
    {
        "Id": 5591,
        "_tab": "<flatbuffers.table.Table object at 0x7fc1b8215210>"
    },
    {
        "Id": 5592,
        "_tab": "<flatbuffers.table.Table object at 0x7fc1acee9360>"
    },
    {
        "Id": 5593,
        "_tab": "<flatbuffers.table.Table object at 0x7fc1b87386d0>"
    },
    {
        "Id": 5594,
        "_tab": "<flatbuffers.table.Table object at 0x7fc1ac8a8100>"
    },
    {
        "Id": 5595,
        "_tab": "<flatbuffers.table.Table object at 0x7fc1ac8a8970>"
    },
    {
        "Id": 5596,
        "_tab": "<flatbuffers.table.Table object at 0x7fc1ac8ab4f0>"
    },
    {
        "Id": 5597,
        "_tab": "<flatbuffers.table.Table object at 0x7fc1ad0a8b20>"
    },
    {
        "Id": 5598,
        "_tab": "<flatbuffers.table.Table object at 0x7fc1b810a140>"
    },
    {
        "Id": 5599,
        "_tab": "<flatbuffers.table.Table object at 0x7fc1b81096c0>"
    },
    {
        "Id": 5600,
        "_tab": "<flatbuffers.table.Table object at 0x7fc1acefc820>"
    },
    {
        "Id": 5601,
        "_tab": "<flatbuffers.table.Table object at 0x7fc1acefdba0>"
    },
    {
        "Id": 5602,
        "_tab": "<flatbuffers.table.Table object at 0x7fc1b8157c10>"
    },
    {
        "Id": 5603,
        "_tab": "<flatbuffers.table.Table object at 0x7fc1b8157670>"
    },
    {
        "Id": 5604,
        "_tab": "<flatbuffers.table.Table object at 0x7fc1b1a453c0>"
    },
    {
        "Id": 5605,
        "_tab": "<flatbuffers.table.Table object at 0x7fc1b1a45900>"
    },
    {
        "Id": 5606,
        "_tab": "<flatbuffers.table.Table object at 0x7fc1b1a45e40>"
    },
    {
        "Id": 5607,
        "_tab": "<flatbuffers.table.Table object at 0x7fc1b1a47d30>"
    },
    {
        "Id": 5608,
        "_tab": "<flatbuffers.table.Table object at 0x7fc1b1a459c0>"
    },
    {
        "Id": 5609,
        "_tab": "<flatbuffers.table.Table object at 0x7fc1acc557e0>"
    },
    {
        "Id": 5610,
        "_tab": "<flatbuffers.table.Table object at 0x7fc1acc54a90>"
    },
    {
        "Id": 5611,
        "_tab": "<flatbuffers.table.Table object at 0x7fc1acc54ca0>"
    },
    {
        "Id": 5612,
        "_tab": "<flatbuffers.table.Table object at 0x7fc1ac268430>"
    },
    {
        "Id": 5613,
        "_tab": "<flatbuffers.table.Table object at 0x7fc1aceeb7c0>"
    },
    {
        "Id": 5614,
        "_tab": "<flatbuffers.table.Table object at 0x7fc1acee81c0>"
    },
    {
        "Id": 5615,
        "_tab": "<flatbuffers.table.Table object at 0x7fc1b842d990>"
    },
    {
        "Id": 5616,
        "_tab": "<flatbuffers.table.Table object at 0x7fc1aceea110>"
    },
    {
        "Id": 5617,
        "_tab": "<flatbuffers.table.Table object at 0x7fc1ac26aec0>"
    },
    {
        "Id": 5618,
        "_tab": "<flatbuffers.table.Table object at 0x7fc1acc579d0>"
    },
    {
        "Id": 5619,
        "_tab": "<flatbuffers.table.Table object at 0x7fc1acc56290>"
    },
    {
        "Id": 5620,
        "_tab": "<flatbuffers.table.Table object at 0x7fc1acc56650>"
    },
    {
        "Id": 5621,
        "_tab": "<flatbuffers.table.Table object at 0x7fc1acc57610>"
    },
    {
        "Id": 5622,
        "_tab": "<flatbuffers.table.Table object at 0x7fc1b1a467a0>"
    },
    {
        "Id": 5623,
        "_tab": "<flatbuffers.table.Table object at 0x7fc1b1a47070>"
    },
    {
        "Id": 5624,
        "_tab": "<flatbuffers.table.Table object at 0x7fc1b1a460b0>"
    },
    {
        "Id": 5625,
        "_tab": "<flatbuffers.table.Table object at 0x7fc1b1a44670>"
    },
    {
        "Id": 5626,
        "_tab": "<flatbuffers.table.Table object at 0x7fc1b81567d0>"
    },
    {
        "Id": 5627,
        "_tab": "<flatbuffers.table.Table object at 0x7fc1b81544f0>"
    },
    {
        "Id": 5628,
        "_tab": "<flatbuffers.table.Table object at 0x7fc1b875fe50>"
    }
]